turkic_translit/__init__.py
turkic_translit/cli.py
turkic_translit/core.py
turkic_translit/lang_filter.py
turkic_translit/langid.py
turkic_translit/logging_config.py
turkic_translit/model_utils.py
turkic_translit/patches.py
turkic_translit/pipeline.py
turkic_translit/sanity.py
turkic_translit/tokenizer.py
turkic_translit/transliterate.py
turkic_translit/cli/__init__.py
turkic_translit/cli/_net_utils.py
turkic_translit/cli/build_spm.py
turkic_translit/cli/corpora.yaml
turkic_translit/cli/download_corpus.py
turkic_translit/cli/eval_lm.py
turkic_translit/cli/filter_russian.py
turkic_translit/cli/pyicu_install.py
turkic_translit/cli/run_leven.py
turkic_translit/cli/train_lm.py
turkic_translit/lm/__init__.py
turkic_translit/lm/data.py
turkic_translit/lm/eval.py
turkic_translit/lm/similarity.py
turkic_translit/lm/tokenizer.py
turkic_translit/lm/train.py
turkic_translit/rules/ar_lat.rules
turkic_translit/rules/kk_ipa.rules
turkic_translit/rules/kk_lat2023.rules
turkic_translit/rules/ky_ipa.rules
turkic_translit/rules/ky_lat2023.rules
turkic_translit/web/__init__.py
turkic_translit/web/web_demo.py
turkic_translit/web/web_utils.py
turkic_transliterate-0.1.8.dist-info/licenses/LICENSE
turkic_transliterate-0.1.8.dist-info/METADATA
turkic_transliterate-0.1.8.dist-info/WHEEL
turkic_transliterate-0.1.8.dist-info/entry_points.txt
turkic_transliterate-0.1.8.dist-info/top_level.txt
turkic_transliterate-0.1.8.dist-info/RECORD
