Metadata-Version: 2.4
Name: turkic-transliterate
Version: 0.1.8
Summary: Deterministic Latin and IPA transliteration for Kazakh, Kyrgyz, plus tokenizer/glue scripts.
Author-email: Austin Wagner <awagner@uci.edu>
License-Expression: MIT
Keywords: kazakh,kyrgyz,transliteration,ipa
Classifier: Programming Language :: Python :: 3
Classifier: Programming Language :: Python :: 3.10
Classifier: Programming Language :: Python :: 3.11
Classifier: Programming Language :: Python :: 3.12
Classifier: Programming Language :: Python :: 3.13
Classifier: Operating System :: OS Independent
Classifier: Intended Audience :: Developers
Classifier: Intended Audience :: Science/Research
Classifier: Topic :: Software Development :: Libraries
Classifier: Topic :: Text Processing :: Linguistic
Requires-Python: >=3.9
License-File: LICENSE
Requires-Dist: epitran<1.27,>=1.0
Requires-Dist: fasttext-wheel==0.9.2
Requires-Dist: numpy<2
Requires-Dist: packaging>=23.0
Requires-Dist: panphon<0.22,>=0.20
Requires-Dist: PyICU>=2.15
Requires-Dist: pytest>=8.0
Requires-Dist: rapidfuzz>=3.5
Requires-Dist: rich>=13.7
Requires-Dist: sentencepiece>=0.2.0
Requires-Dist: click>=8.1
Requires-Dist: types-requests>=2.31
Requires-Dist: datasets>=2.20
Requires-Dist: evaluate>=0.4
Requires-Dist: accelerate>=0.28
Requires-Dist: transformers<5,>=4.41
Requires-Dist: tqdm>=4.66
Requires-Dist: scikit-learn>=1.4
Requires-Dist: typing_extensions>=4.12
Provides-Extra: examples
Requires-Dist: flask; extra == "examples"
Requires-Dist: streamlit; extra == "examples"
Requires-Dist: jupyterlab; extra == "examples"
Provides-Extra: winlid
Provides-Extra: corpus
Requires-Dist: datasets>=2.20; extra == "corpus"
Requires-Dist: pyarrow>=14.0; extra == "corpus"
Requires-Dist: requests>=2.0; extra == "corpus"
Provides-Extra: dev
Requires-Dist: black>=23.0; extra == "dev"
Requires-Dist: ruff>=0.2.0; extra == "dev"
Requires-Dist: mypy>=1.0; extra == "dev"
Requires-Dist: pytest>=8.0; extra == "dev"
Requires-Dist: build>=1.0; extra == "dev"
Requires-Dist: twine>=4.0; extra == "dev"
Requires-Dist: make>=0.1.6; extra == "dev"
Requires-Dist: types-requests>=2.31; extra == "dev"
Provides-Extra: ui
Requires-Dist: gradio>=4.0; extra == "ui"
Requires-Dist: pandas; extra == "ui"
Requires-Dist: matplotlib>=3.9; extra == "ui"
Dynamic: license-file
